{
   "agent": "tokio-websockets-simd",
   "behavior": "OK",
   "behaviorClose": "OK",
   "case": 61,
   "closedByMe": false,
   "createStats": true,
   "createWirelog": true,
   "description": "Repeated 2x: Continuation Frame with FIN = true (where there is nothing to continue), then text Message fragmented into 2 fragments.",
   "droppedByMe": false,
   "duration": 1,
   "expectation": "The connection is failed immediately, since there is no message to continue.",
   "expected": {
      "OK": []
   },
   "expectedClose": {
      "closeCode": [
         1002
      ],
      "closedByMe": false,
      "requireClean": false
   },
   "failedByMe": false,
   "httpRequest": "GET / HTTP/1.1\r\nUser-Agent: AutobahnTestSuite/0.8.2-0.10.9\r\nHost: 127.0.0.1:9004\r\nUpgrade: WebSocket\r\nConnection: Upgrade\r\nPragma: no-cache\r\nCache-Control: no-cache\r\nSec-WebSocket-Key: zqC4+YtMWsX8e+Z9UhYLoA==\r\nSec-WebSocket-Version: 13\r\n\r\n",
   "httpResponse": "HTTP/1.1 101 Switching Protocols\r\nUpgrade: websocket\r\nConnection: Upgrade\r\nSec-WebSocket-Accept: cBbDkhO9hB26E73oKyabrflTfFI=\r\n\r\n",
   "id": "5.17",
   "isServer": false,
   "localCloseCode": null,
   "localCloseReason": null,
   "received": [],
   "remoteCloseCode": null,
   "remoteCloseReason": null,
   "reportCompressionRatio": false,
   "reportTime": false,
   "result": "Actual events match at least one expected.",
   "resultClose": "Connection was properly closed",
   "rxFrameStats": {},
   "rxOctetStats": {
      "129": 1
   },
   "started": "2024-12-19T10:28:48.228Z",
   "trafficStats": null,
   "txFrameStats": {
      "0": 4,
      "1": 2
   },
   "txOctetStats": {
      "15": 6,
      "240": 1
   },
   "wasClean": false,
   "wasCloseHandshakeTimeout": false,
   "wasNotCleanReason": "peer dropped the TCP connection without previous WebSocket closing handshake",
   "wasOpenHandshakeTimeout": false,
   "wasServerConnectionDropTimeout": false,
   "wirelog": [
      [
         "TO",
         [
            240,
            "474554202f20485454502f312e310d0a557365722d4167656e743a204175746f6261686e5465737453756974652f302e382e322d302e31302e390d0a486f7374 ..."
         ],
         false
      ],
      [
         "RO",
         [
            129,
            "485454502f312e312031303120537769746368696e672050726f746f636f6c730d0a557067726164653a20776562736f636b65740d0a436f6e6e656374696f6e ..."
         ]
      ],
      [
         "TF",
         [
            9,
            "fragment1"
         ],
         0,
         true,
         0,
         "b94300c2",
         null,
         null,
         false
      ],
      [
         "TO",
         [
            15,
            "8089b94300c2df3161a5d4266eb688"
         ],
         false
      ],
      [
         "TF",
         [
            9,
            "fragment2"
         ],
         1,
         false,
         0,
         "39a79aa7",
         null,
         null,
         false
      ],
      [
         "TO",
         [
            15,
            "018939a79aa75fd5fbc054c2f4d30b"
         ],
         false
      ],
      [
         "TF",
         [
            9,
            "fragment3"
         ],
         0,
         true,
         0,
         "23cde9e6",
         null,
         null,
         false
      ],
      [
         "TO",
         [
            15,
            "808923cde9e645bf88814ea8879210"
         ],
         false
      ],
      [
         "TF",
         [
            9,
            "fragment1"
         ],
         0,
         true,
         0,
         "1c6e0459",
         null,
         null,
         false
      ],
      [
         "TO",
         [
            15,
            "80891c6e04597a1c653e710b6a2d2d"
         ],
         false
      ],
      [
         "TF",
         [
            9,
            "fragment2"
         ],
         1,
         false,
         0,
         "0db3ad51",
         null,
         null,
         false
      ],
      [
         "TO",
         [
            15,
            "01890db3ad516bc1cc3660d6c3253f"
         ],
         false
      ],
      [
         "TF",
         [
            9,
            "fragment3"
         ],
         0,
         true,
         0,
         "67142986",
         null,
         null,
         false
      ],
      [
         "TO",
         [
            15,
            "808967142986016648e10a7147f254"
         ],
         false
      ],
      [
         "KL",
         1
      ]
   ]
}