{
   "agent": "tokio-websockets",
   "behavior": "OK",
   "behaviorClose": "OK",
   "case": 73,
   "closedByMe": false,
   "createStats": true,
   "createWirelog": true,
   "description": "Send invalid UTF-8 text message in fragments of 1 octet, resulting in frames ending on positions which are not code point ends.<br><br>MESSAGE:<br>cebae1bdb9cf83cebcceb5eda080656469746564",
   "droppedByMe": false,
   "duration": 1,
   "expectation": "The connection is failed immediately, since the payload is not valid UTF-8.",
   "expected": {
      "OK": []
   },
   "expectedClose": {
      "closeCode": [
         1007
      ],
      "closedByMe": false,
      "closedByWrongEndpointIsFatal": true,
      "requireClean": false
   },
   "failedByMe": false,
   "httpRequest": "GET / HTTP/1.1\r\nUser-Agent: AutobahnTestSuite/25.10.1-0.10.9\r\nHost: 127.0.0.1:9006\r\nUpgrade: WebSocket\r\nConnection: Upgrade\r\nPragma: no-cache\r\nCache-Control: no-cache\r\nSec-WebSocket-Key: Pq/1B7kfrNZw59HXKaF/nA==\r\nSec-WebSocket-Version: 13\r\n\r\n",
   "httpResponse": "HTTP/1.1 101 Switching Protocols\r\nUpgrade: websocket\r\nConnection: Upgrade\r\nSec-WebSocket-Accept: T/Zg+1+KjjWiaf5hBCN27UBJyxg=\r\n\r\n",
   "id": "6.3.2",
   "isServer": false,
   "localCloseCode": null,
   "localCloseReason": null,
   "received": [],
   "remoteCloseCode": null,
   "remoteCloseReason": null,
   "reportCompressionRatio": false,
   "reportTime": false,
   "result": "Actual events match at least one expected.",
   "resultClose": "Connection was properly closed",
   "rxFrameStats": {},
   "rxOctetStats": {
      "129": 1
   },
   "started": "2026-01-27T04:29:06.442Z",
   "trafficStats": null,
   "txFrameStats": {
      "0": 20,
      "1": 1
   },
   "txOctetStats": {
      "6": 1,
      "7": 20,
      "242": 1
   },
   "wasClean": false,
   "wasCloseHandshakeTimeout": false,
   "wasNotCleanReason": "peer dropped the TCP connection without previous WebSocket closing handshake",
   "wasOpenHandshakeTimeout": false,
   "wasServerConnectionDropTimeout": false,
   "wirelog": [
      [
         "TO",
         [
            242,
            "474554202f20485454502f312e310d0a557365722d4167656e743a204175746f6261686e5465737453756974652f32352e31302e312d302e31302e390d0a486f ..."
         ],
         false
      ],
      [
         "RO",
         [
            129,
            "485454502f312e312031303120537769746368696e672050726f746f636f6c730d0a557067726164653a20776562736f636b65740d0a436f6e6e656374696f6e ..."
         ]
      ],
      [
         "TF",
         [
            1,
            "0xce"
         ],
         1,
         false,
         0,
         "dbc3317a",
         null,
         null,
         false
      ],
      [
         "TO",
         [
            7,
            "0181dbc3317a15"
         ],
         false
      ],
      [
         "TF",
         [
            1,
            "0xba"
         ],
         0,
         false,
         0,
         "3d95c25f",
         null,
         null,
         false
      ],
      [
         "TO",
         [
            7,
            "00813d95c25f87"
         ],
         false
      ],
      [
         "TF",
         [
            1,
            "0xe1"
         ],
         0,
         false,
         0,
         "7a0133eb",
         null,
         null,
         false
      ],
      [
         "TO",
         [
            7,
            "00817a0133eb9b"
         ],
         false
      ],
      [
         "TF",
         [
            1,
            "0xbd"
         ],
         0,
         false,
         0,
         "cceb7882",
         null,
         null,
         false
      ],
      [
         "TO",
         [
            7,
            "0081cceb788271"
         ],
         false
      ],
      [
         "TF",
         [
            1,
            "0xb9"
         ],
         0,
         false,
         0,
         "b64317a2",
         null,
         null,
         false
      ],
      [
         "TO",
         [
            7,
            "0081b64317a20f"
         ],
         false
      ],
      [
         "TF",
         [
            1,
            "0xcf"
         ],
         0,
         false,
         0,
         "e7f75c3c",
         null,
         null,
         false
      ],
      [
         "TO",
         [
            7,
            "0081e7f75c3c28"
         ],
         false
      ],
      [
         "TF",
         [
            1,
            "0x83"
         ],
         0,
         false,
         0,
         "56808e55",
         null,
         null,
         false
      ],
      [
         "TO",
         [
            7,
            "008156808e55d5"
         ],
         false
      ],
      [
         "TF",
         [
            1,
            "0xce"
         ],
         0,
         false,
         0,
         "607978d2",
         null,
         null,
         false
      ],
      [
         "TO",
         [
            7,
            "0081607978d2ae"
         ],
         false
      ],
      [
         "TF",
         [
            1,
            "0xbc"
         ],
         0,
         false,
         0,
         "189eec31",
         null,
         null,
         false
      ],
      [
         "TO",
         [
            7,
            "0081189eec31a4"
         ],
         false
      ],
      [
         "TF",
         [
            1,
            "0xce"
         ],
         0,
         false,
         0,
         "e361ef87",
         null,
         null,
         false
      ],
      [
         "TO",
         [
            7,
            "0081e361ef872d"
         ],
         false
      ],
      [
         "TF",
         [
            1,
            "0xb5"
         ],
         0,
         false,
         0,
         "ea07fa34",
         null,
         null,
         false
      ],
      [
         "TO",
         [
            7,
            "0081ea07fa345f"
         ],
         false
      ],
      [
         "TF",
         [
            1,
            "0xed"
         ],
         0,
         false,
         0,
         "2b93ed9b",
         null,
         null,
         false
      ],
      [
         "TO",
         [
            7,
            "00812b93ed9bc6"
         ],
         false
      ],
      [
         "TF",
         [
            1,
            "0xa0"
         ],
         0,
         false,
         0,
         "e1de2953",
         null,
         null,
         false
      ],
      [
         "TO",
         [
            7,
            "0081e1de295341"
         ],
         false
      ],
      [
         "TF",
         [
            1,
            "0x80"
         ],
         0,
         false,
         0,
         "c19a53a8",
         null,
         null,
         false
      ],
      [
         "TO",
         [
            7,
            "0081c19a53a841"
         ],
         false
      ],
      [
         "TF",
         [
            1,
            "e"
         ],
         0,
         false,
         0,
         "27b1b85f",
         null,
         null,
         false
      ],
      [
         "TO",
         [
            7,
            "008127b1b85f42"
         ],
         false
      ],
      [
         "TF",
         [
            1,
            "d"
         ],
         0,
         false,
         0,
         "ea1f2db2",
         null,
         null,
         false
      ],
      [
         "TO",
         [
            7,
            "0081ea1f2db28e"
         ],
         false
      ],
      [
         "TF",
         [
            1,
            "i"
         ],
         0,
         false,
         0,
         "14e39e29",
         null,
         null,
         false
      ],
      [
         "TO",
         [
            7,
            "008114e39e297d"
         ],
         false
      ],
      [
         "TF",
         [
            1,
            "t"
         ],
         0,
         false,
         0,
         "ca905353",
         null,
         null,
         false
      ],
      [
         "TO",
         [
            7,
            "0081ca905353be"
         ],
         false
      ],
      [
         "TF",
         [
            1,
            "e"
         ],
         0,
         false,
         0,
         "36b91153",
         null,
         null,
         false
      ],
      [
         "TO",
         [
            7,
            "008136b9115353"
         ],
         false
      ],
      [
         "TF",
         [
            1,
            "d"
         ],
         0,
         false,
         0,
         "7a6cf724",
         null,
         null,
         false
      ],
      [
         "TO",
         [
            7,
            "00817a6cf7241e"
         ],
         false
      ],
      [
         "TF",
         [
            0,
            ""
         ],
         0,
         true,
         0,
         "7da3a067",
         null,
         null,
         false
      ],
      [
         "TO",
         [
            6,
            "80807da3a067"
         ],
         false
      ],
      [
         "KL",
         1
      ]
   ]
}