{
   "agent": "tokio-tungstenite",
   "behavior": "OK",
   "behaviorClose": "OK",
   "case": 301,
   "closedByMe": true,
   "createStats": true,
   "createWirelog": true,
   "description": "Send text message with payload of length 65536 auto-fragmented with <b>autoFragmentSize = 1300</b>.",
   "droppedByMe": false,
   "duration": 3,
   "expectation": "Receive echo'ed text message (with payload as sent and transmitted frame counts as expected). Clean close with normal code.",
   "expected": {
      "OK": [
         [
            "message",
            "**************************************************************** ...",
            false
         ]
      ]
   },
   "expectedClose": {
      "closeCode": [
         1000
      ],
      "closedByMe": true,
      "requireClean": true
   },
   "failedByMe": false,
   "httpRequest": "GET / HTTP/1.1\r\nUser-Agent: AutobahnTestSuite/0.8.2-0.10.9\r\nHost: 127.0.0.1:9002\r\nUpgrade: WebSocket\r\nConnection: Upgrade\r\nPragma: no-cache\r\nCache-Control: no-cache\r\nSec-WebSocket-Key: woMuza3vozIfbSraykdzVA==\r\nSec-WebSocket-Version: 13\r\n\r\n",
   "httpResponse": "HTTP/1.1 101 Switching Protocols\r\nconnection: Upgrade\r\nupgrade: websocket\r\nsec-websocket-accept: s+H/fQorCV7Fe01AbRzRvhO/Yi0=\r\n\r\n",
   "id": "10.1.1",
   "isServer": false,
   "localCloseCode": 1000,
   "localCloseReason": null,
   "received": [
      [
         "message",
         "**************************************************************** ...",
         false
      ]
   ],
   "remoteCloseCode": 1000,
   "remoteCloseReason": null,
   "reportCompressionRatio": false,
   "reportTime": false,
   "result": "Actual events match at least one expected.",
   "resultClose": "Connection was properly closed",
   "rxFrameStats": {
      "1": 1,
      "8": 1
   },
   "rxOctetStats": {
      "4": 1,
      "10": 1,
      "129": 1,
      "65536": 1
   },
   "started": "2024-09-13T15:29:06.500Z",
   "trafficStats": null,
   "txFrameStats": {
      "0": 50,
      "1": 1,
      "8": 1
   },
   "txOctetStats": {
      "8": 1,
      "240": 1,
      "544": 1,
      "1308": 50
   },
   "wasClean": true,
   "wasCloseHandshakeTimeout": false,
   "wasNotCleanReason": null,
   "wasOpenHandshakeTimeout": false,
   "wasServerConnectionDropTimeout": false,
   "wirelog": [
      [
         "TO",
         [
            240,
            "474554202f20485454502f312e310d0a557365722d4167656e743a204175746f6261686e5465737453756974652f302e382e322d302e31302e390d0a486f7374 ..."
         ],
         false
      ],
      [
         "RO",
         [
            129,
            "485454502f312e312031303120537769746368696e672050726f746f636f6c730d0a636f6e6e656374696f6e3a20557067726164650d0a757067726164653a20 ..."
         ]
      ],
      [
         "TF",
         [
            1300,
            "**************************************************************** ..."
         ],
         1,
         false,
         0,
         "2bdc0a8a",
         null,
         null,
         false
      ],
      [
         "TO",
         [
            1308,
            "01fe05142bdc0a8a01f620a001f620a001f620a001f620a001f620a001f620a001f620a001f620a001f620a001f620a001f620a001f620a001f620a001f620a0 ..."
         ],
         false
      ],
      [
         "TF",
         [
            1300,
            "**************************************************************** ..."
         ],
         0,
         false,
         0,
         "dbd04f08",
         null,
         null,
         false
      ],
      [
         "TO",
         [
            1308,
            "00fe0514dbd04f08f1fa6522f1fa6522f1fa6522f1fa6522f1fa6522f1fa6522f1fa6522f1fa6522f1fa6522f1fa6522f1fa6522f1fa6522f1fa6522f1fa6522 ..."
         ],
         false
      ],
      [
         "TF",
         [
            1300,
            "**************************************************************** ..."
         ],
         0,
         false,
         0,
         "afbc8224",
         null,
         null,
         false
      ],
      [
         "TO",
         [
            1308,
            "00fe0514afbc82248596a80e8596a80e8596a80e8596a80e8596a80e8596a80e8596a80e8596a80e8596a80e8596a80e8596a80e8596a80e8596a80e8596a80e ..."
         ],
         false
      ],
      [
         "TF",
         [
            1300,
            "**************************************************************** ..."
         ],
         0,
         false,
         0,
         "e2eba139",
         null,
         null,
         false
      ],
      [
         "TO",
         [
            1308,
            "00fe0514e2eba139c8c18b13c8c18b13c8c18b13c8c18b13c8c18b13c8c18b13c8c18b13c8c18b13c8c18b13c8c18b13c8c18b13c8c18b13c8c18b13c8c18b13 ..."
         ],
         false
      ],
      [
         "TF",
         [
            1300,
            "**************************************************************** ..."
         ],
         0,
         false,
         0,
         "386024ac",
         null,
         null,
         false
      ],
      [
         "TO",
         [
            1308,
            "00fe0514386024ac124a0e86124a0e86124a0e86124a0e86124a0e86124a0e86124a0e86124a0e86124a0e86124a0e86124a0e86124a0e86124a0e86124a0e86 ..."
         ],
         false
      ],
      [
         "TF",
         [
            1300,
            "**************************************************************** ..."
         ],
         0,
         false,
         0,
         "97249515",
         null,
         null,
         false
      ],
      [
         "TO",
         [
            1308,
            "00fe051497249515bd0ebf3fbd0ebf3fbd0ebf3fbd0ebf3fbd0ebf3fbd0ebf3fbd0ebf3fbd0ebf3fbd0ebf3fbd0ebf3fbd0ebf3fbd0ebf3fbd0ebf3fbd0ebf3f ..."
         ],
         false
      ],
      [
         "TF",
         [
            1300,
            "**************************************************************** ..."
         ],
         0,
         false,
         0,
         "675d02bf",
         null,
         null,
         false
      ],
      [
         "TO",
         [
            1308,
            "00fe0514675d02bf4d7728954d7728954d7728954d7728954d7728954d7728954d7728954d7728954d7728954d7728954d7728954d7728954d7728954d772895 ..."
         ],
         false
      ],
      [
         "TF",
         [
            1300,
            "**************************************************************** ..."
         ],
         0,
         false,
         0,
         "3b617143",
         null,
         null,
         false
      ],
      [
         "TO",
         [
            1308,
            "00fe05143b617143114b5b69114b5b69114b5b69114b5b69114b5b69114b5b69114b5b69114b5b69114b5b69114b5b69114b5b69114b5b69114b5b69114b5b69 ..."
         ],
         false
      ],
      [
         "TF",
         [
            1300,
            "**************************************************************** ..."
         ],
         0,
         false,
         0,
         "cc508d9b",
         null,
         null,
         false
      ],
      [
         "TO",
         [
            1308,
            "00fe0514cc508d9be67aa7b1e67aa7b1e67aa7b1e67aa7b1e67aa7b1e67aa7b1e67aa7b1e67aa7b1e67aa7b1e67aa7b1e67aa7b1e67aa7b1e67aa7b1e67aa7b1 ..."
         ],
         false
      ],
      [
         "TF",
         [
            1300,
            "**************************************************************** ..."
         ],
         0,
         false,
         0,
         "2094553f",
         null,
         null,
         false
      ],
      [
         "TO",
         [
            1308,
            "00fe05142094553f0abe7f150abe7f150abe7f150abe7f150abe7f150abe7f150abe7f150abe7f150abe7f150abe7f150abe7f150abe7f150abe7f150abe7f15 ..."
         ],
         false
      ],
      [
         "TF",
         [
            1300,
            "**************************************************************** ..."
         ],
         0,
         false,
         0,
         "566f7ba9",
         null,
         null,
         false
      ],
      [
         "TO",
         [
            1308,
            "00fe0514566f7ba97c4551837c4551837c4551837c4551837c4551837c4551837c4551837c4551837c4551837c4551837c4551837c4551837c4551837c455183 ..."
         ],
         false
      ],
      [
         "TF",
         [
            1300,
            "**************************************************************** ..."
         ],
         0,
         false,
         0,
         "310f500f",
         null,
         null,
         false
      ],
      [
         "TO",
         [
            1308,
            "00fe0514310f500f1b257a251b257a251b257a251b257a251b257a251b257a251b257a251b257a251b257a251b257a251b257a251b257a251b257a251b257a25 ..."
         ],
         false
      ],
      [
         "TF",
         [
            1300,
            "**************************************************************** ..."
         ],
         0,
         false,
         0,
         "232e59f2",
         null,
         null,
         false
      ],
      [
         "TO",
         [
            1308,
            "00fe0514232e59f2090473d8090473d8090473d8090473d8090473d8090473d8090473d8090473d8090473d8090473d8090473d8090473d8090473d8090473d8 ..."
         ],
         false
      ],
      [
         "TF",
         [
            1300,
            "**************************************************************** ..."
         ],
         0,
         false,
         0,
         "e49ed61e",
         null,
         null,
         false
      ],
      [
         "TO",
         [
            1308,
            "00fe0514e49ed61eceb4fc34ceb4fc34ceb4fc34ceb4fc34ceb4fc34ceb4fc34ceb4fc34ceb4fc34ceb4fc34ceb4fc34ceb4fc34ceb4fc34ceb4fc34ceb4fc34 ..."
         ],
         false
      ],
      [
         "TF",
         [
            1300,
            "**************************************************************** ..."
         ],
         0,
         false,
         0,
         "3db27201",
         null,
         null,
         false
      ],
      [
         "TO",
         [
            1308,
            "00fe05143db272011798582b1798582b1798582b1798582b1798582b1798582b1798582b1798582b1798582b1798582b1798582b1798582b1798582b1798582b ..."
         ],
         false
      ],
      [
         "TF",
         [
            1300,
            "**************************************************************** ..."
         ],
         0,
         false,
         0,
         "7f6fbb6a",
         null,
         null,
         false
      ],
      [
         "TO",
         [
            1308,
            "00fe05147f6fbb6a5545914055459140554591405545914055459140554591405545914055459140554591405545914055459140554591405545914055459140 ..."
         ],
         false
      ],
      [
         "TF",
         [
            1300,
            "**************************************************************** ..."
         ],
         0,
         false,
         0,
         "f26169b1",
         null,
         null,
         false
      ],
      [
         "TO",
         [
            1308,
            "00fe0514f26169b1d84b439bd84b439bd84b439bd84b439bd84b439bd84b439bd84b439bd84b439bd84b439bd84b439bd84b439bd84b439bd84b439bd84b439b ..."
         ],
         false
      ],
      [
         "TF",
         [
            1300,
            "**************************************************************** ..."
         ],
         0,
         false,
         0,
         "29a24d04",
         null,
         null,
         false
      ],
      [
         "TO",
         [
            1308,
            "00fe051429a24d040388672e0388672e0388672e0388672e0388672e0388672e0388672e0388672e0388672e0388672e0388672e0388672e0388672e0388672e ..."
         ],
         false
      ],
      [
         "TF",
         [
            1300,
            "**************************************************************** ..."
         ],
         0,
         false,
         0,
         "968511c8",
         null,
         null,
         false
      ],
      [
         "TO",
         [
            1308,
            "00fe0514968511c8bcaf3be2bcaf3be2bcaf3be2bcaf3be2bcaf3be2bcaf3be2bcaf3be2bcaf3be2bcaf3be2bcaf3be2bcaf3be2bcaf3be2bcaf3be2bcaf3be2 ..."
         ],
         false
      ],
      [
         "TF",
         [
            1300,
            "**************************************************************** ..."
         ],
         0,
         false,
         0,
         "8e229795",
         null,
         null,
         false
      ],
      [
         "TO",
         [
            1308,
            "00fe05148e229795a408bdbfa408bdbfa408bdbfa408bdbfa408bdbfa408bdbfa408bdbfa408bdbfa408bdbfa408bdbfa408bdbfa408bdbfa408bdbfa408bdbf ..."
         ],
         false
      ],
      [
         "TF",
         [
            1300,
            "**************************************************************** ..."
         ],
         0,
         false,
         0,
         "8e4afbdd",
         null,
         null,
         false
      ],
      [
         "TO",
         [
            1308,
            "00fe05148e4afbdda460d1f7a460d1f7a460d1f7a460d1f7a460d1f7a460d1f7a460d1f7a460d1f7a460d1f7a460d1f7a460d1f7a460d1f7a460d1f7a460d1f7 ..."
         ],
         false
      ],
      [
         "TF",
         [
            1300,
            "**************************************************************** ..."
         ],
         0,
         false,
         0,
         "d673cc64",
         null,
         null,
         false
      ],
      [
         "TO",
         [
            1308,
            "00fe0514d673cc64fc59e64efc59e64efc59e64efc59e64efc59e64efc59e64efc59e64efc59e64efc59e64efc59e64efc59e64efc59e64efc59e64efc59e64e ..."
         ],
         false
      ],
      [
         "TF",
         [
            1300,
            "**************************************************************** ..."
         ],
         0,
         false,
         0,
         "fe2f6162",
         null,
         null,
         false
      ],
      [
         "TO",
         [
            1308,
            "00fe0514fe2f6162d4054b48d4054b48d4054b48d4054b48d4054b48d4054b48d4054b48d4054b48d4054b48d4054b48d4054b48d4054b48d4054b48d4054b48 ..."
         ],
         false
      ],
      [
         "TF",
         [
            1300,
            "**************************************************************** ..."
         ],
         0,
         false,
         0,
         "9765be7c",
         null,
         null,
         false
      ],
      [
         "TO",
         [
            1308,
            "00fe05149765be7cbd4f9456bd4f9456bd4f9456bd4f9456bd4f9456bd4f9456bd4f9456bd4f9456bd4f9456bd4f9456bd4f9456bd4f9456bd4f9456bd4f9456 ..."
         ],
         false
      ],
      [
         "TF",
         [
            1300,
            "**************************************************************** ..."
         ],
         0,
         false,
         0,
         "2086c7bb",
         null,
         null,
         false
      ],
      [
         "TO",
         [
            1308,
            "00fe05142086c7bb0aaced910aaced910aaced910aaced910aaced910aaced910aaced910aaced910aaced910aaced910aaced910aaced910aaced910aaced91 ..."
         ],
         false
      ],
      [
         "TF",
         [
            1300,
            "**************************************************************** ..."
         ],
         0,
         false,
         0,
         "ec8bec2f",
         null,
         null,
         false
      ],
      [
         "TO",
         [
            1308,
            "00fe0514ec8bec2fc6a1c605c6a1c605c6a1c605c6a1c605c6a1c605c6a1c605c6a1c605c6a1c605c6a1c605c6a1c605c6a1c605c6a1c605c6a1c605c6a1c605 ..."
         ],
         false
      ],
      [
         "TF",
         [
            1300,
            "**************************************************************** ..."
         ],
         0,
         false,
         0,
         "26afcec2",
         null,
         null,
         false
      ],
      [
         "TO",
         [
            1308,
            "00fe051426afcec20c85e4e80c85e4e80c85e4e80c85e4e80c85e4e80c85e4e80c85e4e80c85e4e80c85e4e80c85e4e80c85e4e80c85e4e80c85e4e80c85e4e8 ..."
         ],
         false
      ],
      [
         "TF",
         [
            1300,
            "**************************************************************** ..."
         ],
         0,
         false,
         0,
         "c081d525",
         null,
         null,
         false
      ],
      [
         "TO",
         [
            1308,
            "00fe0514c081d525eaabff0feaabff0feaabff0feaabff0feaabff0feaabff0feaabff0feaabff0feaabff0feaabff0feaabff0feaabff0feaabff0feaabff0f ..."
         ],
         false
      ],
      [
         "TF",
         [
            1300,
            "**************************************************************** ..."
         ],
         0,
         false,
         0,
         "e0300abc",
         null,
         null,
         false
      ],
      [
         "TO",
         [
            1308,
            "00fe0514e0300abcca1a2096ca1a2096ca1a2096ca1a2096ca1a2096ca1a2096ca1a2096ca1a2096ca1a2096ca1a2096ca1a2096ca1a2096ca1a2096ca1a2096 ..."
         ],
         false
      ],
      [
         "TF",
         [
            1300,
            "**************************************************************** ..."
         ],
         0,
         false,
         0,
         "ba54fb38",
         null,
         null,
         false
      ],
      [
         "TO",
         [
            1308,
            "00fe0514ba54fb38907ed112907ed112907ed112907ed112907ed112907ed112907ed112907ed112907ed112907ed112907ed112907ed112907ed112907ed112 ..."
         ],
         false
      ],
      [
         "TF",
         [
            1300,
            "**************************************************************** ..."
         ],
         0,
         false,
         0,
         "0eb93269",
         null,
         null,
         false
      ],
      [
         "TO",
         [
            1308,
            "00fe05140eb932692493184324931843249318432493184324931843249318432493184324931843249318432493184324931843249318432493184324931843 ..."
         ],
         false
      ],
      [
         "TF",
         [
            1300,
            "**************************************************************** ..."
         ],
         0,
         false,
         0,
         "5923f4a6",
         null,
         null,
         false
      ],
      [
         "TO",
         [
            1308,
            "00fe05145923f4a67309de8c7309de8c7309de8c7309de8c7309de8c7309de8c7309de8c7309de8c7309de8c7309de8c7309de8c7309de8c7309de8c7309de8c ..."
         ],
         false
      ],
      [
         "TF",
         [
            1300,
            "**************************************************************** ..."
         ],
         0,
         false,
         0,
         "60768859",
         null,
         null,
         false
      ],
      [
         "TO",
         [
            1308,
            "00fe0514607688594a5ca2734a5ca2734a5ca2734a5ca2734a5ca2734a5ca2734a5ca2734a5ca2734a5ca2734a5ca2734a5ca2734a5ca2734a5ca2734a5ca273 ..."
         ],
         false
      ],
      [
         "TF",
         [
            1300,
            "**************************************************************** ..."
         ],
         0,
         false,
         0,
         "7b65c4ad",
         null,
         null,
         false
      ],
      [
         "TO",
         [
            1308,
            "00fe05147b65c4ad514fee87514fee87514fee87514fee87514fee87514fee87514fee87514fee87514fee87514fee87514fee87514fee87514fee87514fee87 ..."
         ],
         false
      ],
      [
         "TF",
         [
            1300,
            "**************************************************************** ..."
         ],
         0,
         false,
         0,
         "cd4b3224",
         null,
         null,
         false
      ],
      [
         "TO",
         [
            1308,
            "00fe0514cd4b3224e761180ee761180ee761180ee761180ee761180ee761180ee761180ee761180ee761180ee761180ee761180ee761180ee761180ee761180e ..."
         ],
         false
      ],
      [
         "TF",
         [
            1300,
            "**************************************************************** ..."
         ],
         0,
         false,
         0,
         "19f6d007",
         null,
         null,
         false
      ],
      [
         "TO",
         [
            1308,
            "00fe051419f6d00733dcfa2d33dcfa2d33dcfa2d33dcfa2d33dcfa2d33dcfa2d33dcfa2d33dcfa2d33dcfa2d33dcfa2d33dcfa2d33dcfa2d33dcfa2d33dcfa2d ..."
         ],
         false
      ],
      [
         "TF",
         [
            1300,
            "**************************************************************** ..."
         ],
         0,
         false,
         0,
         "326569e5",
         null,
         null,
         false
      ],
      [
         "TO",
         [
            1308,
            "00fe0514326569e5184f43cf184f43cf184f43cf184f43cf184f43cf184f43cf184f43cf184f43cf184f43cf184f43cf184f43cf184f43cf184f43cf184f43cf ..."
         ],
         false
      ],
      [
         "TF",
         [
            1300,
            "**************************************************************** ..."
         ],
         0,
         false,
         0,
         "920080b0",
         null,
         null,
         false
      ],
      [
         "TO",
         [
            1308,
            "00fe0514920080b0b82aaa9ab82aaa9ab82aaa9ab82aaa9ab82aaa9ab82aaa9ab82aaa9ab82aaa9ab82aaa9ab82aaa9ab82aaa9ab82aaa9ab82aaa9ab82aaa9a ..."
         ],
         false
      ],
      [
         "TF",
         [
            1300,
            "**************************************************************** ..."
         ],
         0,
         false,
         0,
         "76f33707",
         null,
         null,
         false
      ],
      [
         "TO",
         [
            1308,
            "00fe051476f337075cd91d2d5cd91d2d5cd91d2d5cd91d2d5cd91d2d5cd91d2d5cd91d2d5cd91d2d5cd91d2d5cd91d2d5cd91d2d5cd91d2d5cd91d2d5cd91d2d ..."
         ],
         false
      ],
      [
         "TF",
         [
            1300,
            "**************************************************************** ..."
         ],
         0,
         false,
         0,
         "afc112c0",
         null,
         null,
         false
      ],
      [
         "TO",
         [
            1308,
            "00fe0514afc112c085eb38ea85eb38ea85eb38ea85eb38ea85eb38ea85eb38ea85eb38ea85eb38ea85eb38ea85eb38ea85eb38ea85eb38ea85eb38ea85eb38ea ..."
         ],
         false
      ],
      [
         "TF",
         [
            1300,
            "**************************************************************** ..."
         ],
         0,
         false,
         0,
         "821669d3",
         null,
         null,
         false
      ],
      [
         "TO",
         [
            1308,
            "00fe0514821669d3a83c43f9a83c43f9a83c43f9a83c43f9a83c43f9a83c43f9a83c43f9a83c43f9a83c43f9a83c43f9a83c43f9a83c43f9a83c43f9a83c43f9 ..."
         ],
         false
      ],
      [
         "TF",
         [
            1300,
            "**************************************************************** ..."
         ],
         0,
         false,
         0,
         "cc21642e",
         null,
         null,
         false
      ],
      [
         "TO",
         [
            1308,
            "00fe0514cc21642ee60b4e04e60b4e04e60b4e04e60b4e04e60b4e04e60b4e04e60b4e04e60b4e04e60b4e04e60b4e04e60b4e04e60b4e04e60b4e04e60b4e04 ..."
         ],
         false
      ],
      [
         "TF",
         [
            1300,
            "**************************************************************** ..."
         ],
         0,
         false,
         0,
         "b1964d24",
         null,
         null,
         false
      ],
      [
         "TO",
         [
            1308,
            "00fe0514b1964d249bbc670e9bbc670e9bbc670e9bbc670e9bbc670e9bbc670e9bbc670e9bbc670e9bbc670e9bbc670e9bbc670e9bbc670e9bbc670e9bbc670e ..."
         ],
         false
      ],
      [
         "TF",
         [
            1300,
            "**************************************************************** ..."
         ],
         0,
         false,
         0,
         "b03b3f39",
         null,
         null,
         false
      ],
      [
         "TO",
         [
            1308,
            "00fe0514b03b3f399a1115139a1115139a1115139a1115139a1115139a1115139a1115139a1115139a1115139a1115139a1115139a1115139a1115139a111513 ..."
         ],
         false
      ],
      [
         "TF",
         [
            1300,
            "**************************************************************** ..."
         ],
         0,
         false,
         0,
         "f3a48835",
         null,
         null,
         false
      ],
      [
         "TO",
         [
            1308,
            "00fe0514f3a48835d98ea21fd98ea21fd98ea21fd98ea21fd98ea21fd98ea21fd98ea21fd98ea21fd98ea21fd98ea21fd98ea21fd98ea21fd98ea21fd98ea21f ..."
         ],
         false
      ],
      [
         "TF",
         [
            1300,
            "**************************************************************** ..."
         ],
         0,
         false,
         0,
         "ebdf0fc6",
         null,
         null,
         false
      ],
      [
         "TO",
         [
            1308,
            "00fe0514ebdf0fc6c1f525ecc1f525ecc1f525ecc1f525ecc1f525ecc1f525ecc1f525ecc1f525ecc1f525ecc1f525ecc1f525ecc1f525ecc1f525ecc1f525ec ..."
         ],
         false
      ],
      [
         "TF",
         [
            1300,
            "**************************************************************** ..."
         ],
         0,
         false,
         0,
         "17931808",
         null,
         null,
         false
      ],
      [
         "TO",
         [
            1308,
            "00fe0514179318083db932223db932223db932223db932223db932223db932223db932223db932223db932223db932223db932223db932223db932223db93222 ..."
         ],
         false
      ],
      [
         "TF",
         [
            1300,
            "**************************************************************** ..."
         ],
         0,
         false,
         0,
         "094e5191",
         null,
         null,
         false
      ],
      [
         "TO",
         [
            1308,
            "00fe0514094e519123647bbb23647bbb23647bbb23647bbb23647bbb23647bbb23647bbb23647bbb23647bbb23647bbb23647bbb23647bbb23647bbb23647bbb ..."
         ],
         false
      ],
      [
         "TF",
         [
            1300,
            "**************************************************************** ..."
         ],
         0,
         false,
         0,
         "839c24af",
         null,
         null,
         false
      ],
      [
         "TO",
         [
            1308,
            "00fe0514839c24afa9b60e85a9b60e85a9b60e85a9b60e85a9b60e85a9b60e85a9b60e85a9b60e85a9b60e85a9b60e85a9b60e85a9b60e85a9b60e85a9b60e85 ..."
         ],
         false
      ],
      [
         "TF",
         [
            1300,
            "**************************************************************** ..."
         ],
         0,
         false,
         0,
         "7877a764",
         null,
         null,
         false
      ],
      [
         "TO",
         [
            1308,
            "00fe05147877a764525d8d4e525d8d4e525d8d4e525d8d4e525d8d4e525d8d4e525d8d4e525d8d4e525d8d4e525d8d4e525d8d4e525d8d4e525d8d4e525d8d4e ..."
         ],
         false
      ],
      [
         "TF",
         [
            536,
            "**************************************************************** ..."
         ],
         0,
         true,
         0,
         "60f04fb6",
         null,
         null,
         false
      ],
      [
         "TO",
         [
            544,
            "80fe021860f04fb64ada659c4ada659c4ada659c4ada659c4ada659c4ada659c4ada659c4ada659c4ada659c4ada659c4ada659c4ada659c4ada659c4ada659c ..."
         ],
         false
      ],
      [
         "KL",
         10
      ],
      [
         "RO",
         [
            65536,
            "817f00000000000100002a2a2a2a2a2a2a2a2a2a2a2a2a2a2a2a2a2a2a2a2a2a2a2a2a2a2a2a2a2a2a2a2a2a2a2a2a2a2a2a2a2a2a2a2a2a2a2a2a2a2a2a2a2a ..."
         ]
      ],
      [
         "RO",
         [
            10,
            "2a2a2a2a2a2a2a2a2a2a"
         ]
      ],
      [
         "RF",
         [
            65536,
            "**************************************************************** ..."
         ],
         1,
         true,
         0,
         false,
         null
      ],
      [
         "TF",
         [
            2,
            "0x03e8"
         ],
         8,
         true,
         0,
         "6a70ef7b",
         null,
         null,
         false
      ],
      [
         "TO",
         [
            8,
            "88826a70ef7b6998"
         ],
         false
      ],
      [
         "RO",
         [
            4,
            "880203e8"
         ]
      ],
      [
         "RF",
         [
            2,
            "0x03e8"
         ],
         8,
         true,
         0,
         false,
         null
      ]
   ]
}